coopr.os-1.0.4-py2.7-nspkg.pth
coopr/os/__init__.py
coopr/os/OSrL.py
coopr/os/OSSolverService.py
coopr/os/plugins/__init__.py
coopr/os/plugins/OSiL_writer.py
coopr/os/plugins/OSrL_reader.py
coopr/os/plugins/ossolver.py
coopr/os/tests/__init__.py
coopr/os/tests/test_cached.py
coopr/os/tests/test_os.py
coopr.os-1.0.4.dist-info/DESCRIPTION.rst
coopr.os-1.0.4.dist-info/entry_points.txt
coopr.os-1.0.4.dist-info/METADATA
coopr.os-1.0.4.dist-info/metadata.json
coopr.os-1.0.4.dist-info/namespace_packages.txt
coopr.os-1.0.4.dist-info/RECORD
coopr.os-1.0.4.dist-info/top_level.txt
coopr.os-1.0.4.dist-info/WHEEL
