Metadata-Version: 2.0
Name: coopr.os
Version: 1.0.4
Summary: Coopr interfaces to the COIN-OR Optimization Services project.
Home-page: https://software.sandia.gov/svn/public/coopr/coopr.os
Author: William Hart
Author-email: wehart@sandia.gov
License: BSD
Keywords: optimization
Platform: any
Classifier: Development Status :: 4 - Beta
Classifier: Intended Audience :: End Users/Desktop
Classifier: Intended Audience :: Science/Research
Classifier: License :: OSI Approved :: BSD License
Classifier: Natural Language :: English
Classifier: Operating System :: Microsoft :: Windows
Classifier: Operating System :: Unix
Classifier: Programming Language :: Python
Classifier: Programming Language :: Unix Shell
Classifier: Topic :: Scientific/Engineering :: Mathematics
Classifier: Topic :: Software Development :: Libraries :: Python Modules
Classifier: Topic :: Scientific/Engineering
